Workbook

Sheet SP riclassificato dati
C2: N | D2: N-1 | G2: N | H2: N-1 | K2: N | L2: N-1
B3: Disponibilità liquide | C3: =+C4+C5 -> 671883 | D3: =+D4+D5 -> 243883 | F3: Immobilizzazioni immateriali | G3: =+G4+G5 -> 500000 | H3: =+H4+H5 -> 144000 | J3: Capitale proprio | K3: =SUM(K4:K8) -> 9646500 | L3: =SUM(L4:L8) -> 7950000
B4: Depositi bancari | C4: 572050 | D4: 198000 | F4: Costi di impianto e di ampliamento | G4: 180000 | J4: Capitale | K4: 7500000 | L4: 6000000
B5: Denaro e valori in cassa | C5: 99833 | D5: 45883 | F5: Diritti di brevetto industr, ecc.. | G5: 320000 | H5: 144000 | J5: Riserva soprapprezzo azioni | K5: 142500
J6: Riserva legale | K6: 1322700 | L6: 1275000
C7: N | D7: N-1 | G7: N | H7: N-1 | J7: Altre riserve | K7: 681300 | L7: 675000
B8: Disponibilità finanziarie | C8: =+C10+C9 -> 2794500 | D8: =+D10+D9 -> 2022000 | F8: Debiti a breve scadenza | G8: =SUM(G9:G16) -> 3589783 | H8: =SUM(H9:H16) -> 4541383
B9: Crediti v/ clienti | C9: 2587500 | D9: 1815000 | F9: Debiti v/banche | G9: 453000 | H9: 723000
B10: Ratei e risconti attivi | C10: 207000 | D10: 207000 | F10: Debiti v/ fornitori | G10: 1687500 | H10: 2070000
F11: Debiti tributari | G11: 635400 | H11: 630000
C12: N | D12: N-1 | F12: Debiti v/ istituti previdenziali | G12: 723000 | H12: 1027500
B13: Rimanenze | C13: =+C14+C15+C16 -> 2602500 | D13: =+D14+D15+D16 -> 2445000 | F13: Altri debiti | G13: 34479 | H13: 34479
B14: Materie prime | C14: 1380000 | D14: 1275000 | F14: Ratei e risconti passivi | G14: 56404 | H14: 56404
B15: Prodotti finiti e merci | C15: 1222500 | D15: 1170000
C18: N | D18: N-1 | G18: N | H18: N-1
B19: Immobilizzazioni materiali | C19: =+C20+C22+C21+C23 -> 10799000 | D19: =+D20+D22+D21+D23 -> 11560500 | F19: Debiti a M.L. scadenza | G19: =+G21+G22+G20 -> 3000000 | H19: =+H21+H22+H20 -> 2970000
B20: Terreni e fabbricati | C20: 4095000 | D20: 4315500 | F20: Fondo manutenzioni programmate | G20: 750000 | H20: 720000
B21: Impianti e macchinari | C21: 4245000 | D21: 4785000 | F21: Obbligazioni | G21: 2250000 | H21: 2250000
B22: Attrezzature industriali | C22: 1971000 | D22: 2028000
B23: Altri beni | C23: 488000 | D23: 432000

Sheet S.P. Riclassificato
B1: SP RICLASSIFICATO SECONDO I CRITERI FINANZIARI
B3: IMPIEGHI | C3: 31/12/N | D3: 31/12/N-1 | F3: FONTI | G3: 31/12/N | H3: 31/12/N-1
B4: Attivo corrente | C4: =+C5+C6+C7 -> 6068883 | D4: =+D5+D6+D7 -> 4710883 | F4: Capitale di debito | G4: =+G5+G6 -> 6589783 | H4: =+H5+H6 -> 7511383
B5: Disponibilità liquide | C5: =+'SP riclassificato dati'!C3 -> 671883 | D5: =+'SP riclassificato dati'!D3 -> 243883 | F5: Debiti a breve scadenza | G5: =+'SP riclassificato dati'!G8 -> 3589783 | H5: =+'SP riclassificato dati'!H8 -> 4541383
B6: Disponibilità finanziarie | C6: =+'SP riclassificato dati'!C8 -> 2794500 | D6: =+'SP riclassificato dati'!D8 -> 2022000 | F6: Debiti a M.L. scadenza | G6: =+'SP riclassificato dati'!G19 -> 3000000 | H6: =+'SP riclassificato dati'!H19 -> 2970000
B7: Rimanenze | C7: =+'SP riclassificato dati'!C13 -> 2602500 | D7: =+'SP riclassificato dati'!D13 -> 2445000 | F7: Patrimonio netto | G7: =+G8+G9 -> 10778100 | H7: =+H8+H9 -> 8904000
B8: Attivo immobilizzato | C8: =+C9+C10+C11 -> 11299000 | D8: =+D9+D10+D11 -> 11704500 | F8: Capitale proprio | G8: =+'SP riclassificato dati'!K3 -> 9646500 | H8: =+'SP riclassificato dati'!L3 -> 7950000
B9: Immobilizzazioni materiali | C9: =+'SP riclassificato dati'!C19 -> 10799000 | D9: =+'SP riclassificato dati'!D19 -> 11560500 | F9: Reddito d'esercizio | G9: 1131600 | H9: 954000
B10: Immobilizzazioni immateriali | C10: =+'SP riclassificato dati'!G3 -> 500000 | D10: =+'SP riclassificato dati'!H3 -> 144000 | F10: TOTALE FONTI | G10: =+G4+G7 -> 17367883 | H10: =+H4+H7 -> 16415383
B11: Immobilizzazioni finanziarie
B12: TOTALE IMPIEGHI | C12: =+C4+C8 -> 17367883 | D12: =+D4+D8 -> 16415383

Sheet Debiti funzionam - finanziam
B2: Debiti di funzionamento | C2: 31/12/N | D2: 31/12/N-1 | G2: Debiti di finanziamento | H2: 31/12/N+1 | I2: 31/12/N
B3: Debiti v/ fornitori | C3: 1687500 | D3: 2070000 | E3: =+C3-D3 -> -382500 | G3: Obbligazioni | H3: 2250000 | I3: 2250000
B4: Debiti tributari | C4: 635400 | D4: 630000 | E4: =+C4-D4 -> 5400 | G4: Debiti v/banche | H4: 453000 | I4: 723000
B5: Debiti v/ istituti previdenziali | C5: 723000 | D5: 1027500 | E5: =+C5-D5 -> -304500
B6: Altri debiti | C6: 34479 | D6: 34479 | E6: =+C6-D6 -> 0
B7: TOTALE DEBITI DI FUNZIONAMENTO | C7: =SUM(C3:C6) -> 3080379 | D7: =SUM(D3:D6) -> 3761979 | E7: =+C7-D7 -> -681600

Sheet Rendiconto finanziario D.L.
C2: FLUSSO FINANZIARIO DELL'ATTIVITA' OPERATIVA
C3: Utile d'esercizio | D3: =+'S.P. Riclassificato'!G9 -> 1131600
C4: Altri ricavi e proventi (plusvalenze) | D4: -20000 | E4: (Ricavo non monetario)
C5: Ammortamenti e svalutazioni imm. immat. | D5: 149000 | E5: (Costo non monetario)
C6: Ammortamenti e svalutazioni imm. mat. | D6: 2286500 | E6: (Costo non monetario)
C7: Altri accantonamenti | D7: 30000 | E7: (Costo non monetario)
C8: - Aumento crediti a breve | D8: =-'SP riclassificato dati'!C9+'SP riclassificato dati'!D9 -> -772500
C9: + Aumento rimanenze | D9: =-('S.P. Riclassificato'!C7-'S.P. Riclassificato'!D7) -> -157500 | G9: N | H9: N-1 | I9: Var.
C10: Ratei e risconti attivi | D10: =-'SP riclassificato dati'!C10+'SP riclassificato dati'!D10 -> 0 | F10: Depositi bancari e postali | G10: =+'SP riclassificato dati'!C4 -> 572050 | H10: =+'SP riclassificato dati'!D4 -> 198000 | I10: =+G10-H10 -> 374050
C11: + Aumento debiti funzionamento | D11: =-('Debiti funzionam - finanziam'!D7-'Debiti funzionam - finanziam'!C7) -> -681600 | F11: Denaro in banca | G11: =+'SP riclassificato dati'!C5 -> 99833 | H11: =+'SP riclassificato dati'!D5 -> 45883 | I11: =+G11-H11 -> 53950
C12: Ratei e risconti passivi | D12: =+'SP riclassificato dati'!G14-'SP riclassificato dati'!H14 -> 0 | F12: Disponibilità liquide | G12: =+G10+G11 -> 671883 | H12: =+H10+H11 -> 243883 | I12: =+G12-H12 -> 428000
C13: TOTALE FLUSSO FINANZIARIO ATTIVITA' OPERATIVA | D13: =SUM(D3:D12) -> 1965500
C15: FLUSSO FINANZIARIO ATTIVITA' DI INVESTIMENTO | F15: Disponibilità liquide al 31/12/N-1 | H15: =+H12 -> 243883
C16: Acquisto imm. materiali | D16: =-(900000+450000+250000) -> -1600000 | F16: Flusso attività operativa | H16: =+D13 -> 1965500
C17: Vendita imm. materiali | D17: 95000 | F17: Flusso attività investimento | H17: =+D19 -> -1785000
C18: Costruzioni in economia (diritti brevetto) | D18: -280000 | F18: Flusso attività finanziamento | H18: =+D27 -> 247500
C19: FLUSSO FINANZIARIO ATTIVITA' DI INVESTIMENTO | D19: =+D16+D17+D18 -> -1785000 | F19: Disponibilità liquide al 31/12/N | H19: =+H15+H16+H17+H18 -> 671883
C22: FLUSSO FINANZIARIO ATTIVITA' DI FINANZIAMENTO
C23: Debiti v/ banche | D23: =-('Debiti funzionam - finanziam'!I4-'Debiti funzionam - finanziam'!H4) -> -270000
C24: Dividendi | D24: -900000
C25: Aumento di capitale | D25: =150000*10.95 -> 1642500
C26: Pagamento costi impianto (x aumento capitale) | D26: -225000
C27: FLUSSO FINANZIARIO ATTIVITA' DI INVESTIMENTO | D27: =+D23+D24+D25+D26 -> 247500
