Workbook

Sheet SP riclassificato dati
C2: N | D2: N-1 | G2: N | H2: N-1 | K2: N | L2: N-1
B3: Disponibilità liquide | C3: =+C4+C5 -> 39000 | D3: =+D4+D5 -> 69000 | F3: Immobilizzazioni immateriali | G3: =+G4+G5 -> 507000 | H3: =+H4+H5 -> 150000 | J3: Capitale proprio | K3: =SUM(K4:K7) -> 4415000 | L3: =SUM(L4:L7) -> 3080000
B4: Depositi bancari e postali | C4: 30000 | D4: 65000 | F4: Diritti brevetto industriale | G4: 507000 | H4: 150000 | J4: Capitale sociale | K4: 3600000 | L4: 2400000
B5: Denaro e valori in cassa | C5: 9000 | D5: 4000 | J5: Riserva soprapprezzo | K5: 330000
G6: N | H6: N-1 | J6: Riserva legale | K6: 480000 | L6: 480000
C7: N | D7: N-1 | F7: Debiti a breve scadenza | G7: =SUM(G8:G16) -> 3832420 | H7: =SUM(H8:H16) -> 2806500 | J7: Altre riserve | K7: 5000 | L7: 200000
B8: Disponibilità finanziarie | C8: =+C9+C10 -> 3566500 | D8: =+D9+D10 -> 2772500 | F8: TFR corrisposto ai dipendenti | H8: 277500
B9: Crediti v/ clienti | C9: 3538000 | D9: 2757500 | F9: Obbligazioni in scadenza | G9: 300000 | H9: 300000
B10: Ratei e risconti attivi | C10: 28500 | D10: 15000 | F10: Debiti v/ altri finanziatori | G10: =705000-630000 -> 75000 | H10: 75000
F11: Debiti v/ banche | G11: 1132500 | H11: 230500
C12: N | D12: N-1 | F12: Debiti v/ fornitori | G12: 1475000 | H12: 1357500
B13: Rimanenze | C13: =+C14+C15 -> 2010000 | D13: =+D14+D15 -> 1590000 | F13: Debiti tributari | G13: 217500 | H13: 76500
B14: Materie prime, suss, consum. | C14: 696000 | D14: 636000 | F14: Debiti v/ istituti previdenziali | G14: 153240 | H14: 111000
B15: Prodotti finiti e merci | C15: 1314000 | D15: 954000 | F15: Deviti v/ altri | G15: 381680 | H15: 288500
F16: Ratei e risconti passivi | G16: 97500 | H16: 90000
C17: N | D17: N-1
B18: Immobilizzazioni materiali | C18: =+C19+C21+C20+C22 -> 4681500 | D18: =+D19+D21+D20+D22 -> 3367500 | G18: N | H18: N-1
B19: Terreni e fabbricati | C19: 2385000 | D19: 1965000 | F19: Debiti a M.L. scadenza | G19: =+G21+G22+G20 -> 2196580 | H19: =+H21+H22+H20 -> 2257500
B20: Impianti e macchinari | C20: 1830000 | D20: 1200000 | F20: TFR | G20: 666580 | H20: =930000-277500 -> 652500
B21: Attrezzature industriali e commerciali | C21: 255000 | D21: 180000 | F21: Obbligazioni | G21: 900000 | H21: =1500000-300000 -> 1200000
B22: Altri beni | C22: 211500 | D22: 22500 | F22: Debiti v/ altri finanziatori | G22: 630000 | H22: =480000-75000 -> 405000

Sheet S.P. Riclassificato
B1: SP RICLASSIFICATO SECONDO I CRITERI FINANZIARI
B3: IMPIEGHI | C3: 31/12/N | D3: 31/12/N-1 | F3: FONTI | G3: 31/12/N | H3: 31/12/N-1
B4: Attivo corrente | C4: =SUM(C5:C7) -> 5615500 | D4: =SUM(D5:D7) -> 4431500 | F4: Capitale di debito | G4: =+G5+G6 -> 6029000 | H4: =+H5+H6 -> 5064000
B5: Disponibilità liquide | C5: =+'SP riclassificato dati'!C3 -> 39000 | D5: =+'SP riclassificato dati'!D3 -> 69000 | F5: Debiti a breve scadenza | G5: =+'SP riclassificato dati'!G7 -> 3832420 | H5: =+'SP riclassificato dati'!H7 -> 2806500
B6: Disponibilità finanziarie | C6: =+'SP riclassificato dati'!C8 -> 3566500 | D6: =+'SP riclassificato dati'!D8 -> 2772500 | F6: Debiti a M.L. scadenza | G6: =+'SP riclassificato dati'!G19 -> 2196580 | H6: =+'SP riclassificato dati'!H19 -> 2257500
B7: Rimanenze | C7: =+'SP riclassificato dati'!C13 -> 2010000 | D7: =+'SP riclassificato dati'!D13 -> 1590000 | F7: Patrimonio netto | G7: =+G8+G9 -> 4775000 | H7: =+H8+H9 -> 2885000
B8: Attivo immobilizzato | C8: =+C9+C10+C11 -> 5188500 | D8: =+D9+D10+D11 -> 3517500 | F8: Capitale proprio | G8: =+'SP riclassificato dati'!K3 -> 4415000 | H8: =+'SP riclassificato dati'!L3 -> 3080000
B9: Immobilizzazioni materiali | C9: =+'SP riclassificato dati'!C18 -> 4681500 | D9: =+'SP riclassificato dati'!D18 -> 3367500 | F9: Reddito d'esercizio | G9: 360000 | H9: -195000
B10: Immobilizzazioni immateriali | C10: =+'SP riclassificato dati'!G3 -> 507000 | D10: =+'SP riclassificato dati'!H3 -> 150000 | F10: TOTALE FONTI | G10: =+G4+G7 -> 10804000 | H10: =+H4+H7 -> 7949000
B11: Immobilizzazioni finanziarie
B12: TOTALE IMPIEGHI | C12: =+C4+C8 -> 10804000 | D12: =+D4+D8 -> 7949000

Sheet Debiti funzionam - finanziam
B2: Debiti di funzionamento | C2: 31/12/N | D2: 31/12/N-1 | G2: Debiti di finanziamento | H2: 31/12/N | I2: 31/12/N-1
B3: TFR corrisposto ai dipendenti | D3: 277500 | G3: Obbligazioni | H3: 1200000 | I3: 1500000
B4: Debiti v/ fornitori | C4: 1475000 | D4: 1357500 | G4: Debiti v/ banche | H4: 1132500 | I4: 230500
B5: Debiti tributari | C5: 217500 | D5: 76500 | G5: Debiti v/ altri finanziatori | H5: 705000 | I5: 480000
B6: Debiti v/ istituti previdenziali | C6: 153240 | D6: 111000 | G6: TOTALE | H6: =+H3+H4+H5 -> 3037500 | I6: =+I3+I4+I5 -> 2210500
B7: Debiti v/ altri | C7: 381680 | D7: 288500 | E7: Variazione
B8: TOTALE | C8: =SUM(C3:C7) -> 2227420 | D8: =SUM(D3:D7) -> 2111000 | E8: =+C8-D8 -> 116420

Sheet Rendiconto finanziario D.L.
C2: FLUSSO FINANZIARIO DELL'ATTIVITA' OPERATIVA
C3: Utile d'esercizio | D3: 360000
C4: - Plusvalenza Impianti e macchinari | D4: -60000 | E4: (ricavo non monetario)
C5: + TFR | D5: 14080 | E5: (costo non monetario)
C6: + Amm.to imm. immat. | D6: 255000 | E6: (costo non monetario)
C7: + Amm.to imm. materiali | D7: 726000 | E7: (costo non monetario)
C8: - Aumento crediti a breve termine | D8: =-('SP riclassificato dati'!C9-'SP riclassificato dati'!D9) -> -780500
C9: - Aumento rimanenze | D9: =+'S.P. Riclassificato'!D7-'S.P. Riclassificato'!C7 -> -420000
C10: - Aumento ratei e risconti attivi | D10: =-('SP riclassificato dati'!C10-'SP riclassificato dati'!D10) -> -13500 | G10: N | H10: N-1 | I10: Var.
C11: + Aumento debiti funzionamento breve termine | D11: =+'Debiti funzionam - finanziam'!C8-'Debiti funzionam - finanziam'!D8 -> 116420 | F11: Depositi bancari e postali | G11: 30000 | H11: 65000 | I11: =+G11-H11 -> -35000
C12: + Aumento ratei e risconti passivi | D12: =+('SP riclassificato dati'!G16-'SP riclassificato dati'!H16) -> 7500 | F12: Denaro in banca | G12: 9000 | H12: 4000 | I12: =+G12-H12 -> 5000
C13: Variazione dei fondi rischi e oneri di breve scadenza | D13: 0 | F13: Disponibilità liquide | G13: =+G11+G12 -> 39000 | H13: =+H11+H12 -> 69000 | I13: =+G13-H13 -> -30000
C14: TOTALE FLUSSO FINANZIARIO ATTIVITA' OPERATIVA | D14: =SUM(D3:D12) -> 205000
C16: FLUSSO FINANZIARIO ATTIVITA' DI INVESTIMENTO | F16: Disponibilità liquide al 31/12/N-1 | H16: =+H13 -> 69000
C17: Acquisto immobilizzazioni immateriali | D17: -612000 | F17: Flusso attività operativa | H17: =+D14 -> 205000
C18: Acquisto immobilizzazioni materiali | D18: =- (150000+225000+1440000) -> -1815000 | F18: Flusso attività investimento | H18: =+D21 -> -2592000
C19: Vendite immobilizzazioni materiali | D19: 585000 | F19: Flusso attività finanziamento | H19: =+D29 -> 2357000
C20: Costruzioni interne | D20: =- (210000+540000) -> -750000 | F20: Disponibilità liquide al 31/12/N | H20: =+H16+H17+H18+H19 -> 39000
C21: FLUSSO FINANZIARIO ATTIVITA' DI INVESTIMENTO | D21: =SUM(D17:D20) -> -2592000
C23: FLUSSO FINANZIARIO ATTIVITA' DI FINANZIAMENTO
C24: Debiti v/ banche | D24: =1132500-230500 -> 902000
C25: Rimborso obbligazioni | D25: -300000
C26: Aumento capitale sociale | D26: =12000*(100+27.5) -> 1530000
C27: Rimborso debiti altri finanziatori | D27: -75000
C28: Accensione debiti altri finanziatori | D28: 300000
C29: FLUSSO FINANZIARIO ATTIVITA' DI INVESTIMENTO | D29: =SUM(D24:D28) -> 2357000
