Workbook

Sheet SP riclassificato dati
C2: N | D2: N-1 | G2: N | H2: N-1 | K2: N | L2: N-1
B3: Disponibilità liquide | C3: =+C4+C5 -> 573270 | D3: =+D4+D5 -> 240045 | F3: Immobilizzazioni immateriali | G3: =+G4+G5 -> 150000 | H3: =+H4+H5 -> 135000 | J3: Capitale proprio | K3: =SUM(K4:K7) -> 5393214 | L3: =SUM(L4:L7) -> 5363214
B4: Depositi bancari e postali | C4: 545520 | D4: 231045 | F4: Diritti brevetto industriale, ecc.. | G4: 150000 | H4: 135000 | J4: Capitale proprio | K4: 3000000 | L4: 3000000
B5: Denaro e valori in cassa | C5: 27750 | D5: 9000 | J5: Riserva legale | K5: 1221000 | L5: 1200000
G6: N | H6: N-1 | J6: Altre riserve | K6: 1172214 | L6: 1163214
C7: N | D7: N-1 | F7: Debiti a breve scadenza | G7: =SUM(G8:G15) -> 4123131 | H7: =SUM(H8:H15) -> 3917331
B8: Disponibilità finanziarie | C8: =+C9+C10 -> 3835500 | D8: =+D9+D10 -> 3645000 | F8: Obbligazioni in scadenza | G8: =3600000-2700000 -> 900000 | H8: 900000
B9: Crediti verso clienti | C9: 3750000 | D9: 3600000 | F9: Debiti v/ banche | G9: 750000 | H9: 726000
B10: Ratei e risconti attivi | C10: 85500 | D10: 45000 | F10: Debiti v/ fornitori | G10: 1575000 | H10: 1576200
F11: Debiti tributari | G11: 398700 | H11: 229500
C12: N | D12: N-1 | F12: Debiti v/ istituti previdenza | G12: 322500 | H12: 331200
B13: Rimanenze | C13: =+C14+C15+C16 -> 2500500 | D13: =+D14+D15+D16 -> 2550000 | F13: Altri debiti | G13: 34431 | H13: 34431
B14: Materie prime, sussid,… | C14: 870000 | D14: 900000 | F14: Ratei e risconti passivi | G14: 142500 | H14: 120000
B15: Prodotti in corso di lavorazione | C15: 355500 | D15: 450000
B16: Prodotti finiti e merci | C16: 1275000 | D16: 1200000
G17: N | H17: N-1
C18: N | D18: N-1 | F18: Debiti a M.L. scadenza | G18: =+G20+G21+G19 -> 2700000 | H18: =+H20+H21+H19 -> 3600000
B19: Immobilizzazioni materiali | C19: =+C20+C22+C21 -> 5434575 | D19: =+D20+D22+D21 -> 6730500 | F19: Obbligazioni | G19: 2700000 | H19: =-900000+4500000 -> 3600000
B20: Terreni e fabbricati | C20: 3174000 | D20: 3279000
B21: Impianti e macchinari | C21: 2179575 | D21: 3330000
B22: Altri beni | C22: 81000 | D22: 121500

Sheet S.P. Riclassificato
B1: SP RICLASSIFICATO SECONDO I CRITERI FINANZIARI
B3: IMPIEGHI | C3: 31/12/N | D3: 31/12/N-1 | F3: FONTI | G3: 31/12/N | H3: 31/12/N-1
B4: Attivo corrente | C4: =+C5+C6+C7 -> 6909270 | D4: =+D5+D6+D7 -> 6435045 | F4: Capitale di debito | G4: =+G5+G6 -> 6823131 | H4: =+H5+H6 -> 7517331
B5: Disponibilità liquide | C5: =+'SP riclassificato dati'!C3 -> 573270 | D5: =+'SP riclassificato dati'!D3 -> 240045 | F5: Debiti a breve scadenza | G5: =+'SP riclassificato dati'!G7 -> 4123131 | H5: =+'SP riclassificato dati'!H7 -> 3917331
B6: Disponibilità finanziarie | C6: =+'SP riclassificato dati'!C8 -> 3835500 | D6: =+'SP riclassificato dati'!D8 -> 3645000 | F6: Debiti a M.L. scadenza | G6: =+'SP riclassificato dati'!G18 -> 2700000 | H6: =+'SP riclassificato dati'!H18 -> 3600000
B7: Rimanenze | C7: =+'SP riclassificato dati'!C13 -> 2500500 | D7: =+'SP riclassificato dati'!D13 -> 2550000 | F7: Patrimonio netto | G7: =+G8+G9 -> 5670714 | H7: =+H8+H9 -> 5783214
B8: Attivo immobilizzato | C8: =+C9+C10+C11 -> 5584575 | D8: =+D9+D10+D11 -> 6865500 | F8: Capitale proprio | G8: =+'SP riclassificato dati'!K3 -> 5393214 | H8: =+'SP riclassificato dati'!L3 -> 5363214
B9: Immobilizzazioni materiali | C9: =+'SP riclassificato dati'!C19 -> 5434575 | D9: =+'SP riclassificato dati'!D19 -> 6730500 | F9: Reddito d'esercizio | G9: 277500 | H9: 420000
B10: Immobilizzazioni immateriali | C10: =+'SP riclassificato dati'!G3 -> 150000 | D10: =+'SP riclassificato dati'!H3 -> 135000 | F10: TOTALE FONTI | G10: =+G4+G7 -> 12493845 | H10: =+H4+H7 -> 13300545
B11: Immobilizzazioni finanziarie
B12: TOTALE IMPIEGHI | C12: =+C4+C8 -> 12493845 | D12: =+D4+D8 -> 13300545

Sheet Debiti funzionam - finanziam
B2: Debiti di funzionamento | C2: 31/12/N | D2: 31/12/N-1 | G2: Debiti di finanziamento | H2: 31/12/N | I2: 31/12/N-1
B3: Debiti v/ fornitori | C3: =+'SP riclassificato dati'!G10 -> 1575000 | D3: =+'SP riclassificato dati'!H10 -> 1576200 | E3: =+C3-D3 -> -1200 | G3: Obbligazioni | H3: 3600000 | I3: 4500000
B4: Debiti tributari | C4: 398700 | D4: 229500 | E4: =+C4-D4 -> 169200 | G4: Debiti v/ banche | H4: 750000 | I4: 726000
B5: Debiti v/ istituti previdenza | C5: 322500 | D5: 331200 | E5: =+C5-D5 -> -8700
B6: Altri debiti | C6: 34431 | D6: 34431 | E6: =+C6-D6 -> 0
B7: TOTALE DEBITI DI FUNZIONAMENTO | C7: =SUM(C3:C6) -> 2330631 | D7: =SUM(D3:D6) -> 2171331 | E7: =+C7-D7 -> 159300

Sheet Rendiconto finanziario D.L.
C2: FLUSSO FINANZIARIO DELL'ATTIVITA' OPERATIVA
C3: Utile d'esercizio | D3: =+'S.P. Riclassificato'!G9 -> 277500
C4: Plusvalenze | D4: -20000 | E4: (ricavo non monetario)
C5: Ammortamento immobilizzazioni materiali | D5: 285000 | E5: (costo non monetario) | G5: =+H19-G12 -> 0
C6: Ammortamento immobilizzazioni immateriali | D6: 695925 | E6: (costo non monetario)
C7: - Aumento crediti a breve | D7: =-(+'SP riclassificato dati'!C9-'SP riclassificato dati'!D9) -> -150000
C8: + Aumento rimanenze | D8: =+'S.P. Riclassificato'!D7-'S.P. Riclassificato'!C7 -> 49500
C9: - Aumento ratei e risconti attivi | D9: =-(+'SP riclassificato dati'!C10-'SP riclassificato dati'!D10) -> -40500 | G9: N | H9: N-1 | I9: Var.
C10: + Aumento debiti funzionamento | D10: =+'Debiti funzionam - finanziam'!C7-'Debiti funzionam - finanziam'!D7 -> 159300 | F10: Depositi bancari e postali | G10: =+'SP riclassificato dati'!C4 -> 545520 | H10: =+'SP riclassificato dati'!D4 -> 231045 | I10: =+G10-H10 -> 314475
C11: + Aumento ratei e risconti passivi | D11: =+'SP riclassificato dati'!G14-'SP riclassificato dati'!H14 -> 22500 | F11: Denaro in banca | G11: =+'SP riclassificato dati'!C5 -> 27750 | H11: =+'SP riclassificato dati'!D5 -> 9000 | I11: =+G11-H11 -> 18750
C12: TOTALE FLUSSO FINANZIARIO ATTIVITA' OPERATIVA | D12: =SUM(D3:D11) -> 1279225 | F12: Disponibilità liquide | G12: =+G10+G11 -> 573270 | H12: =+H10+H11 -> 240045 | I12: =+G12-H12 -> 333225
C14: FLUSSO FINANZIARIO ATTIVITA' DI INVESTIMENTO
C15: Acquisto immobilizzazioni immateriali | D15: -300000 | F15: Disponibilità liquide al 31/12/N-1 | H15: =+H12 -> 240045
C16: Vendite immobilizzazioni materiali | D16: 620000 | F16: Flusso attività operativa | H16: =+D12 -> 1279225
C17: FLUSSO FINANZIARIO ATTIVITA' DI INVESTIMENTO | D17: =+D15+D16 -> 320000 | F17: Flusso attività investimento | H17: =+D17 -> 320000
F18: Flusso attività finanziamento | H18: =+D25 -> -1266000
F19: Disponibilità liquide al 31/12/N | H19: =+H15+H16+H17+H18 -> 573270
C21: FLUSSO FINANZIARIO ATTIVITA' DI FINANZIAMENTO
C22: Debiti v/ banche | D22: =+'Debiti funzionam - finanziam'!H4-'Debiti funzionam - finanziam'!I4 -> 24000
C23: Rimborso obbligazioni | D23: =-'Debiti funzionam - finanziam'!I3+'Debiti funzionam - finanziam'!H3 -> -900000
C24: Pagamento dividendi | D24: -390000
C25: FLUSSO FINANZIARIO ATTIVITA' DI INVESTIMENTO | D25: =+D22+D23+D24 -> -1266000
